ml_exam_codes/__init__.py
ml_exam_codes/codes.py
ml_exam_codes-0.1.1.dist-info/LICENSE.txt
ml_exam_codes-0.1.1.dist-info/METADATA
ml_exam_codes-0.1.1.dist-info/WHEEL
ml_exam_codes-0.1.1.dist-info/top_level.txt
ml_exam_codes-0.1.1.dist-info/RECORD
