Metadata-Version: 2.1
Name: ml-exam-codes
Version: 0.1.1
Summary: A library containing ML code snippets for exam preparation
Home-page: https://github.com/yourusername/ml_exam_codes
Author: Your Name
Author-email: your.email@example.com
Classifier: Programming Language :: Python :: 3
Classifier: License :: OSI Approved :: MIT License
Classifier: Operating System :: OS Independent
Requires-Python: >=3.6
License-File: LICENSE.txt
